<?xml version="1.0" encoding="UTF-8"?>
<?xml-stylesheet href="CoreNLP-to-HTML.xsl" type="text/xsl"?>
<root>
  <document>
    <sentences>
    	<sentence id="18">
        <tokens>
          <token id="1">
            <word>US</word>
            <lemma>US</lemma>
            <CharacterOffsetBegin>2092</CharacterOffsetBegin>
            <CharacterOffsetEnd>2094</CharacterOffsetEnd>
            <POS>NNP</POS>
            <NER>LOCATION</NER>
          </token>
          <token id="2">
            <word>and</word>
            <lemma>and</lemma>
            <CharacterOffsetBegin>2095</CharacterOffsetBegin>
            <CharacterOffsetEnd>2098</CharacterOffsetEnd>
            <POS>CC</POS>
            <NER>O</NER>
          </token>
          <token id="3">
            <word>British</word>
            <lemma>British</lemma>
            <CharacterOffsetBegin>2099</CharacterOffsetBegin>
            <CharacterOffsetEnd>2106</CharacterOffsetEnd>
            <POS>NNP</POS>
            <NER>LOCATION</NER>
          </token>
          <token id="4">
            <word>activists</word>
            <lemma>activist</lemma>
            <CharacterOffsetBegin>2107</CharacterOffsetBegin>
            <CharacterOffsetEnd>2116</CharacterOffsetEnd>
            <POS>NNS</POS>
            <NER>O</NER>
          </token>
          <token id="5">
            <word>staged</word>
            <lemma>stage</lemma>
            <CharacterOffsetBegin>2117</CharacterOffsetBegin>
            <CharacterOffsetEnd>2123</CharacterOffsetEnd>
            <POS>VBD</POS>
            <NER>O</NER>
          </token>
          <token id="6">
            <word>a</word>
            <lemma>a</lemma>
            <CharacterOffsetBegin>2124</CharacterOffsetBegin>
            <CharacterOffsetEnd>2125</CharacterOffsetEnd>
            <POS>DT</POS>
            <NER>O</NER>
          </token>
          <token id="7">
            <word>dramatic</word>
            <lemma>dramatic</lemma>
            <CharacterOffsetBegin>2126</CharacterOffsetBegin>
            <CharacterOffsetEnd>2134</CharacterOffsetEnd>
            <POS>JJ</POS>
            <NER>O</NER>
          </token>
          <token id="8">
            <word>protest</word>
            <lemma>protest</lemma>
            <CharacterOffsetBegin>2135</CharacterOffsetBegin>
            <CharacterOffsetEnd>2142</CharacterOffsetEnd>
            <POS>NN</POS>
            <NER>O</NER>
          </token>
          <token id="9">
            <word>in</word>
            <lemma>in</lemma>
            <CharacterOffsetBegin>2143</CharacterOffsetBegin>
            <CharacterOffsetEnd>2145</CharacterOffsetEnd>
            <POS>IN</POS>
            <NER>O</NER>
          </token>
          <token id="10">
            <word>Beijing</word>
            <lemma>Beijing</lemma>
            <CharacterOffsetBegin>2146</CharacterOffsetBegin>
            <CharacterOffsetEnd>2153</CharacterOffsetEnd>
            <POS>NNP</POS>
            <NER>LOCATION</NER>
          </token>
          <token id="11">
            <word>on</word>
            <lemma>on</lemma>
            <CharacterOffsetBegin>2154</CharacterOffsetBegin>
            <CharacterOffsetEnd>2156</CharacterOffsetEnd>
            <POS>IN</POS>
            <NER>O</NER>
          </token>
          <token id="12">
            <word>Wednesday</word>
            <lemma>Wednesday</lemma>
            <CharacterOffsetBegin>2157</CharacterOffsetBegin>
            <CharacterOffsetEnd>2166</CharacterOffsetEnd>
            <POS>NNP</POS>
            <NER>DATE</NER>
            <NormalizedNER>XXXX-WXX-3</NormalizedNER>
            <Timex tid="t1" type="DATE">XXXX-WXX-3</Timex>
          </token>
          <token id="13">
            <word>,</word>
            <lemma>,</lemma>
            <CharacterOffsetBegin>2166</CharacterOffsetBegin>
            <CharacterOffsetEnd>2167</CharacterOffsetEnd>
            <POS>,</POS>
            <NER>O</NER>
          </token>
          <token id="14">
            <word>scaling</word>
            <lemma>scale</lemma>
            <CharacterOffsetBegin>2168</CharacterOffsetBegin>
            <CharacterOffsetEnd>2175</CharacterOffsetEnd>
            <POS>VBG</POS>
            <NER>O</NER>
          </token>
          <token id="15">
            <word>a</word>
            <lemma>a</lemma>
            <CharacterOffsetBegin>2176</CharacterOffsetBegin>
            <CharacterOffsetEnd>2177</CharacterOffsetEnd>
            <POS>DT</POS>
            <NER>O</NER>
          </token>
          <token id="16">
            <word>pole</word>
            <lemma>pole</lemma>
            <CharacterOffsetBegin>2178</CharacterOffsetBegin>
            <CharacterOffsetEnd>2182</CharacterOffsetEnd>
            <POS>NN</POS>
            <NER>O</NER>
          </token>
          <token id="17">
            <word>and</word>
            <lemma>and</lemma>
            <CharacterOffsetBegin>2183</CharacterOffsetBegin>
            <CharacterOffsetEnd>2186</CharacterOffsetEnd>
            <POS>CC</POS>
            <NER>O</NER>
          </token>
          <token id="18">
            <word>unfurling</word>
            <lemma>unfurl</lemma>
            <CharacterOffsetBegin>2187</CharacterOffsetBegin>
            <CharacterOffsetEnd>2196</CharacterOffsetEnd>
            <POS>VBG</POS>
            <NER>O</NER>
          </token>
          <token id="19">
            <word>giant</word>
            <lemma>giant</lemma>
            <CharacterOffsetBegin>2197</CharacterOffsetBegin>
            <CharacterOffsetEnd>2202</CharacterOffsetEnd>
            <POS>JJ</POS>
            <NER>O</NER>
          </token>
          <token id="20">
            <word>''</word>
            <lemma>''</lemma>
            <CharacterOffsetBegin>2203</CharacterOffsetBegin>
            <CharacterOffsetEnd>2205</CharacterOffsetEnd>
            <POS>''</POS>
            <NER>O</NER>
          </token>
          <token id="21">
            <word>Free</word>
            <lemma>Free</lemma>
            <CharacterOffsetBegin>2205</CharacterOffsetBegin>
            <CharacterOffsetEnd>2209</CharacterOffsetEnd>
            <POS>NNP</POS>
            <NER>O</NER>
          </token>
          <token id="22">
            <word>Tibet</word>
            <lemma>Tibet</lemma>
            <CharacterOffsetBegin>2210</CharacterOffsetBegin>
            <CharacterOffsetEnd>2215</CharacterOffsetEnd>
            <POS>NNP</POS>
            <NER>O</NER>
          </token>
          <token id="23">
            <word>''</word>
            <lemma>''</lemma>
            <CharacterOffsetBegin>2215</CharacterOffsetBegin>
            <CharacterOffsetEnd>2217</CharacterOffsetEnd>
            <POS>''</POS>
            <NER>O</NER>
          </token>
          <token id="24">
            <word>banners</word>
            <lemma>banner</lemma>
            <CharacterOffsetBegin>2218</CharacterOffsetBegin>
            <CharacterOffsetEnd>2225</CharacterOffsetEnd>
            <POS>NNS</POS>
            <NER>O</NER>
          </token>
          <token id="25">
            <word>close</word>
            <lemma>close</lemma>
            <CharacterOffsetBegin>2226</CharacterOffsetBegin>
            <CharacterOffsetEnd>2231</CharacterOffsetEnd>
            <POS>RB</POS>
            <NER>O</NER>
          </token>
          <token id="26">
            <word>to</word>
            <lemma>to</lemma>
            <CharacterOffsetBegin>2232</CharacterOffsetBegin>
            <CharacterOffsetEnd>2234</CharacterOffsetEnd>
            <POS>TO</POS>
            <NER>O</NER>
          </token>
          <token id="27">
            <word>the</word>
            <lemma>the</lemma>
            <CharacterOffsetBegin>2235</CharacterOffsetBegin>
            <CharacterOffsetEnd>2238</CharacterOffsetEnd>
            <POS>DT</POS>
            <NER>O</NER>
          </token>
          <token id="28">
            <word>stadium</word>
            <lemma>stadium</lemma>
            <CharacterOffsetBegin>2239</CharacterOffsetBegin>
            <CharacterOffsetEnd>2246</CharacterOffsetEnd>
            <POS>NN</POS>
            <NER>O</NER>
          </token>
          <token id="29">
            <word>where</word>
            <lemma>where</lemma>
            <CharacterOffsetBegin>2247</CharacterOffsetBegin>
            <CharacterOffsetEnd>2252</CharacterOffsetEnd>
            <POS>WRB</POS>
            <NER>O</NER>
          </token>
          <token id="30">
            <word>the</word>
            <lemma>the</lemma>
            <CharacterOffsetBegin>2253</CharacterOffsetBegin>
            <CharacterOffsetEnd>2256</CharacterOffsetEnd>
            <POS>DT</POS>
            <NER>O</NER>
          </token>
          <token id="31">
            <word>Olympics</word>
            <lemma>Olympics</lemma>
            <CharacterOffsetBegin>2257</CharacterOffsetBegin>
            <CharacterOffsetEnd>2265</CharacterOffsetEnd>
            <POS>NNPS</POS>
            <NER>MISC</NER>
          </token>
          <token id="32">
            <word>will</word>
            <lemma>will</lemma>
            <CharacterOffsetBegin>2266</CharacterOffsetBegin>
            <CharacterOffsetEnd>2270</CharacterOffsetEnd>
            <POS>MD</POS>
            <NER>O</NER>
          </token>
          <token id="33">
            <word>open</word>
            <lemma>open</lemma>
            <CharacterOffsetBegin>2271</CharacterOffsetBegin>
            <CharacterOffsetEnd>2275</CharacterOffsetEnd>
            <POS>VB</POS>
            <NER>O</NER>
          </token>
          <token id="34">
            <word>in</word>
            <lemma>in</lemma>
            <CharacterOffsetBegin>2276</CharacterOffsetBegin>
            <CharacterOffsetEnd>2278</CharacterOffsetEnd>
            <POS>IN</POS>
            <NER>O</NER>
          </token>
          <token id="35">
            <word>two</word>
            <lemma>two</lemma>
            <CharacterOffsetBegin>2279</CharacterOffsetBegin>
            <CharacterOffsetEnd>2282</CharacterOffsetEnd>
            <POS>CD</POS>
            <NER>DURATION</NER>
            <Timex tid="t2" type="DURATION">P2D</Timex>
          </token>
          <token id="36">
            <word>days</word>
            <lemma>day</lemma>
            <CharacterOffsetBegin>2283</CharacterOffsetBegin>
            <CharacterOffsetEnd>2287</CharacterOffsetEnd>
            <POS>NNS</POS>
            <NER>NUMBER</NER>
            <NormalizedNER>0.0</NormalizedNER>
            <Timex tid="t2" type="DURATION">P2D</Timex>
          </token>
          <token id="37">
            <word>.</word>
            <lemma>.</lemma>
            <CharacterOffsetBegin>2287</CharacterOffsetBegin>
            <CharacterOffsetEnd>2288</CharacterOffsetEnd>
            <POS>.</POS>
            <NER>O</NER>
          </token>
        </tokens>
        <parse>(ROOT (S (NP (NP (NNP US) (CC and) (NNP British)) (NNS activists)) (VP (VBD staged) (NP (DT a) (JJ dramatic) (NN protest)) (PP (IN in) (NP (NNP Beijing))) (PP (IN on) (NP (NNP Wednesday))) (, ,) (VP (VP (VBG scaling) (NP (DT a) (NN pole))) (CC and) (VP (VBG unfurling) (NP (JJ giant)) ('' '')) (NP (NP (NNP Free) (NNP Tibet)) ('' '') (PP (ADVP (NP (NNS banners)) (RB close)) (TO to) (NP (NP (DT the) (NN stadium)) (SBAR (WHADVP (WRB where)) (S (NP (DT the) (NNPS Olympics)) (VP (MD will) (VP (VB open) (PP (IN in) (NP (CD two) (NNS days)))))))))))) (. .))) </parse>
        <dependencies type="basic-dependencies">
          <dep type="root">
            <governor idx="0">ROOT</governor>
            <dependent idx="5">staged</dependent>
          </dep>
          <dep type="nn">
            <governor idx="4">activists</governor>
            <dependent idx="1">US</dependent>
          </dep>
          <dep type="cc">
            <governor idx="1">US</governor>
            <dependent idx="2">and</dependent>
          </dep>
          <dep type="conj">
            <governor idx="1">US</governor>
            <dependent idx="3">British</dependent>
          </dep>
          <dep type="nsubj">
            <governor idx="5">staged</governor>
            <dependent idx="4">activists</dependent>
          </dep>
          <dep type="det">
            <governor idx="8">protest</governor>
            <dependent idx="6">a</dependent>
          </dep>
          <dep type="amod">
            <governor idx="8">protest</governor>
            <dependent idx="7">dramatic</dependent>
          </dep>
          <dep type="dobj">
            <governor idx="5">staged</governor>
            <dependent idx="8">protest</dependent>
          </dep>
          <dep type="prep">
            <governor idx="5">staged</governor>
            <dependent idx="9">in</dependent>
          </dep>
          <dep type="pobj">
            <governor idx="9">in</governor>
            <dependent idx="10">Beijing</dependent>
          </dep>
          <dep type="prep">
            <governor idx="5">staged</governor>
            <dependent idx="11">on</dependent>
          </dep>
          <dep type="pobj">
            <governor idx="11">on</governor>
            <dependent idx="12">Wednesday</dependent>
          </dep>
          <dep type="dep">
            <governor idx="5">staged</governor>
            <dependent idx="14">scaling</dependent>
          </dep>
          <dep type="det">
            <governor idx="16">pole</governor>
            <dependent idx="15">a</dependent>
          </dep>
          <dep type="dobj">
            <governor idx="14">scaling</governor>
            <dependent idx="16">pole</dependent>
          </dep>
          <dep type="cc">
            <governor idx="14">scaling</governor>
            <dependent idx="17">and</dependent>
          </dep>
          <dep type="conj">
            <governor idx="14">scaling</governor>
            <dependent idx="18">unfurling</dependent>
          </dep>
          <dep type="dobj">
            <governor idx="18">unfurling</governor>
            <dependent idx="19">giant</dependent>
          </dep>
          <dep type="nn">
            <governor idx="22">Tibet</governor>
            <dependent idx="21">Free</dependent>
          </dep>
          <dep type="dobj">
            <governor idx="14">scaling</governor>
            <dependent idx="22">Tibet</dependent>
          </dep>
          <dep type="npadvmod">
            <governor idx="25">close</governor>
            <dependent idx="24">banners</dependent>
          </dep>
          <dep type="advmod">
            <governor idx="26">to</governor>
            <dependent idx="25">close</dependent>
          </dep>
          <dep type="prep">
            <governor idx="22">Tibet</governor>
            <dependent idx="26">to</dependent>
          </dep>
          <dep type="det">
            <governor idx="28">stadium</governor>
            <dependent idx="27">the</dependent>
          </dep>
          <dep type="pobj">
            <governor idx="26">to</governor>
            <dependent idx="28">stadium</dependent>
          </dep>
          <dep type="advmod">
            <governor idx="33">open</governor>
            <dependent idx="29">where</dependent>
          </dep>
          <dep type="det">
            <governor idx="31">Olympics</governor>
            <dependent idx="30">the</dependent>
          </dep>
          <dep type="nsubj">
            <governor idx="33">open</governor>
            <dependent idx="31">Olympics</dependent>
          </dep>
          <dep type="aux">
            <governor idx="33">open</governor>
            <dependent idx="32">will</dependent>
          </dep>
          <dep type="rcmod">
            <governor idx="28">stadium</governor>
            <dependent idx="33">open</dependent>
          </dep>
          <dep type="prep">
            <governor idx="33">open</governor>
            <dependent idx="34">in</dependent>
          </dep>
          <dep type="num">
            <governor idx="36">days</governor>
            <dependent idx="35">two</dependent>
          </dep>
          <dep type="pobj">
            <governor idx="34">in</governor>
            <dependent idx="36">days</dependent>
          </dep>
        </dependencies>
        <dependencies type="collapsed-dependencies">
          <dep type="root">
            <governor idx="0">ROOT</governor>
            <dependent idx="5">staged</dependent>
          </dep>
          <dep type="nn">
            <governor idx="4">activists</governor>
            <dependent idx="1">US</dependent>
          </dep>
          <dep type="conj_and">
            <governor idx="1">US</governor>
            <dependent idx="3">British</dependent>
          </dep>
          <dep type="nsubj">
            <governor idx="5">staged</governor>
            <dependent idx="4">activists</dependent>
          </dep>
          <dep type="det">
            <governor idx="8">protest</governor>
            <dependent idx="6">a</dependent>
          </dep>
          <dep type="amod">
            <governor idx="8">protest</governor>
            <dependent idx="7">dramatic</dependent>
          </dep>
          <dep type="dobj">
            <governor idx="5">staged</governor>
            <dependent idx="8">protest</dependent>
          </dep>
          <dep type="prep_in">
            <governor idx="5">staged</governor>
            <dependent idx="10">Beijing</dependent>
          </dep>
          <dep type="prep_on">
            <governor idx="5">staged</governor>
            <dependent idx="12">Wednesday</dependent>
          </dep>
          <dep type="dep">
            <governor idx="5">staged</governor>
            <dependent idx="14">scaling</dependent>
          </dep>
          <dep type="det">
            <governor idx="16">pole</governor>
            <dependent idx="15">a</dependent>
          </dep>
          <dep type="dobj">
            <governor idx="14">scaling</governor>
            <dependent idx="16">pole</dependent>
          </dep>
          <dep type="conj_and">
            <governor idx="14">scaling</governor>
            <dependent idx="18">unfurling</dependent>
          </dep>
          <dep type="dobj">
            <governor idx="18">unfurling</governor>
            <dependent idx="19">giant</dependent>
          </dep>
          <dep type="nn">
            <governor idx="22">Tibet</governor>
            <dependent idx="21">Free</dependent>
          </dep>
          <dep type="dobj">
            <governor idx="14">scaling</governor>
            <dependent idx="22">Tibet</dependent>
          </dep>
          <dep type="npadvmod">
            <governor idx="22">Tibet</governor>
            <dependent idx="24">banners</dependent>
          </dep>
          <dep type="det">
            <governor idx="28">stadium</governor>
            <dependent idx="27">the</dependent>
          </dep>
          <dep type="prep_close_to">
            <governor idx="22">Tibet</governor>
            <dependent idx="28">stadium</dependent>
          </dep>
          <dep type="advmod">
            <governor idx="33">open</governor>
            <dependent idx="29">where</dependent>
          </dep>
          <dep type="det">
            <governor idx="31">Olympics</governor>
            <dependent idx="30">the</dependent>
          </dep>
          <dep type="nsubj">
            <governor idx="33">open</governor>
            <dependent idx="31">Olympics</dependent>
          </dep>
          <dep type="aux">
            <governor idx="33">open</governor>
            <dependent idx="32">will</dependent>
          </dep>
          <dep type="rcmod">
            <governor idx="28">stadium</governor>
            <dependent idx="33">open</dependent>
          </dep>
          <dep type="num">
            <governor idx="36">days</governor>
            <dependent idx="35">two</dependent>
          </dep>
          <dep type="prep_in">
            <governor idx="33">open</governor>
            <dependent idx="36">days</dependent>
          </dep>
        </dependencies>
        <dependencies type="collapsed-ccprocessed-dependencies">
          <dep type="root">
            <governor idx="0">ROOT</governor>
            <dependent idx="5">staged</dependent>
          </dep>
          <dep type="nn">
            <governor idx="4">activists</governor>
            <dependent idx="1">US</dependent>
          </dep>
          <dep type="conj_and">
            <governor idx="1">US</governor>
            <dependent idx="3">British</dependent>
          </dep>
          <dep type="nn">
            <governor idx="4">activists</governor>
            <dependent idx="3">British</dependent>
          </dep>
          <dep type="nsubj">
            <governor idx="5">staged</governor>
            <dependent idx="4">activists</dependent>
          </dep>
          <dep type="det">
            <governor idx="8">protest</governor>
            <dependent idx="6">a</dependent>
          </dep>
          <dep type="amod">
            <governor idx="8">protest</governor>
            <dependent idx="7">dramatic</dependent>
          </dep>
          <dep type="dobj">
            <governor idx="5">staged</governor>
            <dependent idx="8">protest</dependent>
          </dep>
          <dep type="prep_in">
            <governor idx="5">staged</governor>
            <dependent idx="10">Beijing</dependent>
          </dep>
          <dep type="prep_on">
            <governor idx="5">staged</governor>
            <dependent idx="12">Wednesday</dependent>
          </dep>
          <dep type="dep">
            <governor idx="5">staged</governor>
            <dependent idx="14">scaling</dependent>
          </dep>
          <dep type="det">
            <governor idx="16">pole</governor>
            <dependent idx="15">a</dependent>
          </dep>
          <dep type="dobj">
            <governor idx="14">scaling</governor>
            <dependent idx="16">pole</dependent>
          </dep>
          <dep type="dep">
            <governor idx="5">staged</governor>
            <dependent idx="18">unfurling</dependent>
          </dep>
          <dep type="conj_and">
            <governor idx="14">scaling</governor>
            <dependent idx="18">unfurling</dependent>
          </dep>
          <dep type="dobj">
            <governor idx="18">unfurling</governor>
            <dependent idx="19">giant</dependent>
          </dep>
          <dep type="nn">
            <governor idx="22">Tibet</governor>
            <dependent idx="21">Free</dependent>
          </dep>
          <dep type="dobj">
            <governor idx="14">scaling</governor>
            <dependent idx="22">Tibet</dependent>
          </dep>
          <dep type="npadvmod">
            <governor idx="22">Tibet</governor>
            <dependent idx="24">banners</dependent>
          </dep>
          <dep type="det">
            <governor idx="28">stadium</governor>
            <dependent idx="27">the</dependent>
          </dep>
          <dep type="prep_close_to">
            <governor idx="22">Tibet</governor>
            <dependent idx="28">stadium</dependent>
          </dep>
          <dep type="advmod">
            <governor idx="33">open</governor>
            <dependent idx="29">where</dependent>
          </dep>
          <dep type="det">
            <governor idx="31">Olympics</governor>
            <dependent idx="30">the</dependent>
          </dep>
          <dep type="nsubj">
            <governor idx="33">open</governor>
            <dependent idx="31">Olympics</dependent>
          </dep>
          <dep type="aux">
            <governor idx="33">open</governor>
            <dependent idx="32">will</dependent>
          </dep>
          <dep type="rcmod">
            <governor idx="28">stadium</governor>
            <dependent idx="33">open</dependent>
          </dep>
          <dep type="num">
            <governor idx="36">days</governor>
            <dependent idx="35">two</dependent>
          </dep>
          <dep type="prep_in">
            <governor idx="33">open</governor>
            <dependent idx="36">days</dependent>
          </dep>
        </dependencies>
      </sentence>
    </sentences>
  </document>
</root>